alura/__init__.py
alura/client.py
alura/models.py
alura/wrappers.py
alura_ai-0.3.5.dist-info/LICENSE
alura_ai-0.3.5.dist-info/METADATA
alura_ai-0.3.5.dist-info/WHEEL
alura_ai-0.3.5.dist-info/top_level.txt
alura_ai-0.3.5.dist-info/RECORD
