Metadata-Version: 2.2
Name: alura-ai
Version: 0.3.5
Summary: AI usage tracking and billing SDK
Author-email: Alura AI <support@aluraai.com>
Project-URL: Homepage, https://aluraai.com
Project-URL: Documentation, https://aluraai.com/docs
Project-URL: Repository, https://github.com/alura-ai/alura-python
Project-URL: Issues, https://github.com/alura-ai/alura-python/issues
Keywords: ai,llm,tracking,billing,openai,usage,cost
Classifier: Development Status :: 4 - Beta
Classifier: Intended Audience :: Developers
Classifier: Operating System :: OS Independent
Classifier: Programming Language :: Python :: 3
Classifier: Programming Language :: Python :: 3.8
Classifier: Programming Language :: Python :: 3.9
Classifier: Programming Language :: Python :: 3.10
Classifier: Programming Language :: Python :: 3.11
Classifier: Programming Language :: Python :: 3.12
Requires-Python: >=3.8
License-File: LICENSE
Requires-Dist: requests>=2.25.0
Provides-Extra: openai
Requires-Dist: openai>=1.0.0; extra == "openai"
Provides-Extra: dev
Requires-Dist: pytest; extra == "dev"
Requires-Dist: pytest-asyncio; extra == "dev"
Requires-Dist: black; extra == "dev"
Requires-Dist: mypy; extra == "dev"
